impact_input/__init__.py
impact_input/__main__.py
impact_input/impact_input.py
impact_input-0.0.4.dist-info/LICENSE
impact_input-0.0.4.dist-info/METADATA
impact_input-0.0.4.dist-info/WHEEL
impact_input-0.0.4.dist-info/top_level.txt
impact_input-0.0.4.dist-info/RECORD
