Metadata-Version: 2.1
Name: impact-input
Version: 0.0.4
Summary: Python Class for managing IMPACT-Z/T input files
Author-email: Lucas Malin <lukemalin@gmail.com>
License: MIT License
Project-URL: Homepage, https://github.com/lm314/impact_input
Project-URL: Bug Tracker, https://github.com/lm314/impact_input/issues
Classifier: Programming Language :: Python :: 3
Classifier: License :: OSI Approved :: MIT License
Classifier: Operating System :: OS Independent
Requires-Python: >=3.7
License-File: LICENSE
